pil2ansi.py
pil2ansi-1.0.0.dist-info/LICENSE
pil2ansi-1.0.0.dist-info/METADATA
pil2ansi-1.0.0.dist-info/WHEEL
pil2ansi-1.0.0.dist-info/top_level.txt
pil2ansi-1.0.0.dist-info/RECORD
