Metadata-Version: 2.1
Name: pil2ansi
Version: 1.0.0
Summary: Convert PIL images to ANSI art
Author-email: lostways <andrew@lostways.com>
License: MIT License
Project-URL: homepage, https://github.com/lostways/pil2ansi
Project-URL: repository, https://github.com/lostways/pil2ansi
Keywords: pil,pillow,ansi,art,image,terminal
Requires-Python: >=3.8
License-File: LICENSE
Requires-Dist: pillow
Provides-Extra: dev
Requires-Dist: black ; extra == 'dev'
Requires-Dist: pytest ; extra == 'dev'
Requires-Dist: mypy ; extra == 'dev'
